pyodide_cli/__init__.py
pyodide_cli/__main__.py
pyodide_cli/app.py
pyodide_cli/tests/__init__.py
pyodide_cli/tests/test_cli.py
pyodide_cli/tests/plugin-test/pyproject.toml
pyodide_cli/tests/plugin-test/plugin_test/app.py
pyodide_cli/tests/plugin-test/plugin_test/main.py
pyodide_cli-0.3.0.dist-info/METADATA
pyodide_cli-0.3.0.dist-info/WHEEL
pyodide_cli-0.3.0.dist-info/entry_points.txt
pyodide_cli-0.3.0.dist-info/licenses/LICENSE
pyodide_cli-0.3.0.dist-info/RECORD
