Metadata-Version: 2.4
Name: pyodide-cli
Version: 0.3.0
Summary: "The command line interface for the Pyodide project"
Project-URL: Homepage, https://github.com/pyodide/pyodide
Project-URL: Bug Tracker, https://github.com/pyodide/pyodide/issues
Project-URL: Documentation, https://pyodide.org/en/stable/
Author: Pyodide developers
License-Expression: MPL-2.0
License-File: LICENSE
Classifier: Operating System :: OS Independent
Classifier: Programming Language :: Python :: 3
Requires-Python: >=3.12
Requires-Dist: rich
Requires-Dist: typer
Provides-Extra: test
Requires-Dist: pytest; extra == 'test'
